gp_db_io.py
gp_sqlconnection.py
gp_storage_io.py
genetikaplusIO-0.0.7.dist-info/LICENSE.txt
genetikaplusIO-0.0.7.dist-info/METADATA
genetikaplusIO-0.0.7.dist-info/WHEEL
genetikaplusIO-0.0.7.dist-info/top_level.txt
genetikaplusIO-0.0.7.dist-info/RECORD
