Metadata-Version: 2.1
Name: genetikaplusIO
Version: 0.0.7
Summary: IO for database
Author: Alon Ben Zion
Author-email: alon@genetikaplus.com
License: MIT License
Classifier: Programming Language :: Python :: 3
Classifier: Operating System :: OS Independent
License-File: LICENSE.txt
Requires-Dist: contourpy (==1.0.7)
Requires-Dist: cycler (==0.11.0)
Requires-Dist: et-xmlfile (==1.1.0)
Requires-Dist: fonttools (==4.39.4)
Requires-Dist: greenlet (==2.0.2)
Requires-Dist: kiwisolver (==1.4.4)
Requires-Dist: matplotlib (==3.7.1)
Requires-Dist: numpy (>=1.24.3)
Requires-Dist: openpyxl (==3.1.2)
Requires-Dist: packaging (==23.1)
Requires-Dist: pandas (==2.0.2)
Requires-Dist: psycopg2-binary (==2.9.6)
Requires-Dist: pyparsing (==3.0.9)
Requires-Dist: python-dotenv (==1.0.0)
Requires-Dist: setuptools (==67.8.0)
Requires-Dist: sqlalchemy (==2.0.15)
Requires-Dist: typing-extensions (==4.6.2)
Requires-Dist: wheel (==0.38.4)
